flake8_annotations_coverage/__init__.py
flake8_annotations_coverage/annotations_coverage.py
flake8_annotations_coverage/ast_helpers.py
flake8_annotations_coverage-0.0.6.dist-info/LICENSE
flake8_annotations_coverage-0.0.6.dist-info/METADATA
flake8_annotations_coverage-0.0.6.dist-info/WHEEL
flake8_annotations_coverage-0.0.6.dist-info/entry_points.txt
flake8_annotations_coverage-0.0.6.dist-info/top_level.txt
flake8_annotations_coverage-0.0.6.dist-info/RECORD
