Metadata-Version: 2.1
Name: flake8_annotations_coverage
Version: 0.0.6
Summary: A flake8 extension that checks for type annotations coverage
Home-page: https://github.com/best-doctor/flake8-annotations-coverage
Author: Ilya Lebedev
Author-email: melevir@gmail.com
License: MIT
Keywords: flake8 annotations
Platform: UNKNOWN
Classifier: Environment :: Console
Classifier: Framework :: Flake8
Classifier: Operating System :: OS Independent
Classifier: Topic :: Software Development :: Documentation
Classifier: Topic :: Software Development :: Libraries :: Python Modules
Classifier: Topic :: Software Development :: Quality Assurance
Classifier: Programming Language :: Python
Classifier: Programming Language :: Python :: 3.7
Classifier: Programming Language :: Python :: 3.8
Classifier: Programming Language :: Python :: 3.9
Classifier: Programming Language :: Python :: 3.10
Requires-Python: >=3.7
License-File: LICENSE
